README.txt
setup.py
test.py
docs/EMAP.txt
docs/HISTORY.txt
docs/UCSD.txt
incf/__init__.py
incf.dai.egg-info/PKG-INFO
incf.dai.egg-info/SOURCES.txt
incf.dai.egg-info/dependency_links.txt
incf.dai.egg-info/entry_points.txt
incf.dai.egg-info/namespace_packages.txt
incf.dai.egg-info/not-zip-safe
incf.dai.egg-info/requires.txt
incf.dai.egg-info/top_level.txt
incf/dai/__init__.py
incf/dai/config.py
incf/dai/hub.py
incf/dai/response.py
incf/dai/utils.py
incf/dai/example_responses/aba_DescribeProcess.xml
incf/dai/example_responses/aba_GetCapabilities.xml
incf/dai/example_responses/emage_DescribeProcess.xml
incf/dai/example_responses/emage_GetCapabilities.xml