Metadata-Version: 1.0
Name: incf.dai
Version: 0.7
Summary: Python API for the INCF Digital Atlasing infrastructure
Home-page: http://software.incf.org/software/incfdai
Author: Raphael Ritz
Author-email: raphael.ritz@incf.org
License: GPL
Keywords: WPS INCF "Digital Atlasing"
Platform: UNKNOWN
Classifier: Programming Language :: Python
Classifier: Topic :: Software Development :: Libraries :: Python Modules
